OnspringApiSdk/Endpoints.py
OnspringApiSdk/Enums.py
OnspringApiSdk/Helpers.py
OnspringApiSdk/Models.py
OnspringApiSdk/OnspringClient.py
OnspringApiSdk/__init__.py
OnspringApiSdk-2.0.2.dist-info/LICENSE.txt
OnspringApiSdk-2.0.2.dist-info/METADATA
OnspringApiSdk-2.0.2.dist-info/WHEEL
OnspringApiSdk-2.0.2.dist-info/top_level.txt
OnspringApiSdk-2.0.2.dist-info/RECORD
