Metadata-Version: 2.1
Name: OnspringApiSdk
Version: 2.0.2
Summary: A package for interacting with version 2 of the Onspring API.
Home-page: https://github.com/StevanFreeborn/onspring-api-sdk-python
Author: StevanFreeborn
Author-email: stevan.freeborn@gmail.com
Project-URL: Bug Tracker, https://github.com/StevanFreeborn/onspring-api-sdk-python/issues
Classifier: Programming Language :: Python :: 3
Classifier: License :: OSI Approved :: MIT License
Classifier: Operating System :: OS Independent
Requires-Python: >=3.10
License-File: LICENSE.txt
Requires-Dist: Requests
